setup.py
DPG/__init__.py
DPG/dp_test.py
DPG.egg-info/PKG-INFO
DPG.egg-info/SOURCES.txt
DPG.egg-info/dependency_links.txt
DPG.egg-info/top_level.txt