Metadata-Version: 2.1
Name: DPG
Version: 0.0.1
Summary: A tool for you to generate data without personal information leak with DP technique.
Home-page: UNKNOWN
Author: Michael
Author-email: 
License: UNKNOWN
Platform: UNKNOWN
